{
	"name": "ui_trigger",
	"properties": {
		"annotations": [],
		"runtimeState": "Stopped",
		"pipelines": [
			{
				"pipelineReference": {
					"referenceName": "Full_pipeline_with_email",
					"type": "PipelineReference"
				}
			}
		],
		"type": "BlobEventsTrigger",
		"typeProperties": {
			"blobPathBeginsWith": "/web/blobs/trigger/",
			"blobPathEndsWith": ".txt",
			"ignoreEmptyBlobs": false,
			"scope": "/subscriptions/529ce17b-846b-434d-9b93-6a49ea48ee99/resourceGroups/peregrine-dev/providers/Microsoft.Storage/storageAccounts/peregrineblob",
			"events": [
				"Microsoft.Storage.BlobCreated"
			]
		}
	}
}